WuyunZhishikuDisiBufenFix1/README.md
WuyunZhishikuDisiBufenFix1/__init__.py
WuyunZhishikuDisiBufenFix1/__main__.py
WuyunZhishikuDisiBufenFix1/file.epub
WuyunZhishikuDisiBufenFix1/index.html
WuyunZhishikuDisiBufenFix1/css/__init__.py
WuyunZhishikuDisiBufenFix1/css/annotations.css
WuyunZhishikuDisiBufenFix1/css/main.css
WuyunZhishikuDisiBufenFix1/css/normalize.css
WuyunZhishikuDisiBufenFix1/css/popup.css
WuyunZhishikuDisiBufenFix1/font/__init__.py
WuyunZhishikuDisiBufenFix1/font/fontello.eot
WuyunZhishikuDisiBufenFix1/font/fontello.svg
WuyunZhishikuDisiBufenFix1/font/fontello.ttf
WuyunZhishikuDisiBufenFix1/font/fontello.woff
WuyunZhishikuDisiBufenFix1/img/__init__.py
WuyunZhishikuDisiBufenFix1/img/annotator-glyph-sprite.png
WuyunZhishikuDisiBufenFix1/img/annotator-icon-sprite.png
WuyunZhishikuDisiBufenFix1/img/apple-touch-icon.png
WuyunZhishikuDisiBufenFix1/img/cancelfullscreen.png
WuyunZhishikuDisiBufenFix1/img/close.png
WuyunZhishikuDisiBufenFix1/img/fullscreen.png
WuyunZhishikuDisiBufenFix1/img/loader.gif
WuyunZhishikuDisiBufenFix1/img/menu-icon.png
WuyunZhishikuDisiBufenFix1/img/save.png
WuyunZhishikuDisiBufenFix1/img/saved.png
WuyunZhishikuDisiBufenFix1/img/settings-s.png
WuyunZhishikuDisiBufenFix1/img/settings.png
WuyunZhishikuDisiBufenFix1/img/star.png
WuyunZhishikuDisiBufenFix1/js/__init__.py
WuyunZhishikuDisiBufenFix1/js/epub.js
WuyunZhishikuDisiBufenFix1/js/epub.min.js
WuyunZhishikuDisiBufenFix1/js/epub.min.map
WuyunZhishikuDisiBufenFix1/js/hooks.min.js
WuyunZhishikuDisiBufenFix1/js/hooks.min.map
WuyunZhishikuDisiBufenFix1/js/reader.js
WuyunZhishikuDisiBufenFix1/js/reader.js.map
WuyunZhishikuDisiBufenFix1/js/reader.min.js
WuyunZhishikuDisiBufenFix1/js/reader.min.map
WuyunZhishikuDisiBufenFix1/js/hooks/__init__.py
WuyunZhishikuDisiBufenFix1/js/hooks/extensions/__init__.py
WuyunZhishikuDisiBufenFix1/js/hooks/extensions/highlight.js
WuyunZhishikuDisiBufenFix1/js/libs/__init__.py
WuyunZhishikuDisiBufenFix1/js/libs/jquery.min.js
wuyun_zhishiku_disi_bufen_fix1-2025.3.24.0.dist-info/METADATA
wuyun_zhishiku_disi_bufen_fix1-2025.3.24.0.dist-info/WHEEL
wuyun_zhishiku_disi_bufen_fix1-2025.3.24.0.dist-info/entry_points.txt
wuyun_zhishiku_disi_bufen_fix1-2025.3.24.0.dist-info/top_level.txt
wuyun_zhishiku_disi_bufen_fix1-2025.3.24.0.dist-info/RECORD
